comfy_script/__init__.py
comfy_script/astutil.py
comfy_script/config.py
comfy_script/client/__init__.py
comfy_script/nodes/__init__.py
comfy_script/runtime/__init__.py
comfy_script/runtime/factory.py
comfy_script/runtime/nodes.py
comfy_script/runtime/data/Images.py
comfy_script/runtime/data/__init__.py
comfy_script/runtime/real/__init__.py
comfy_script/runtime/real/nodes.py
comfy_script/transpile/__init__.py
comfy_script/transpile/__main__.py
comfy_script/transpile/prompt.py
comfy_script/transpile/passes/__init__.py
comfy_script/ui/__init__.py
comfy_script/ui/ipy/__init__.py
comfy_script/ui/ipy/image.py
comfy_script/ui/solara/__init__.py
comfy_script/ui/solara/metadata.py
comfy_script-0.5.1.dist-info/METADATA
comfy_script-0.5.1.dist-info/WHEEL
comfy_script-0.5.1.dist-info/entry_points.txt
comfy_script-0.5.1.dist-info/licenses/LICENSE.txt
comfy_script-0.5.1.dist-info/RECORD
