Metadata-Version: 2.1
Name: comfy-script
Version: 0.5.1
Summary: A Python frontend and library for ComfyUI
Project-URL: Homepage, https://github.com/Chaoses-Ib/ComfyScript
Project-URL: Issues, https://github.com/Chaoses-Ib/ComfyScript/issues
Author-email: Chaoses-Ib <Chaos-es@outlook.com>
License-File: LICENSE.txt
Keywords: comfyui
Classifier: License :: OSI Approved :: MIT License
Classifier: Operating System :: OS Independent
Classifier: Programming Language :: Python :: 3
Requires-Python: >=3.9
Provides-Extra: all
Requires-Dist: comfy-script[cli]; extra == 'all'
Requires-Dist: comfy-script[default]; extra == 'all'
Requires-Dist: comfy-script[solara]; extra == 'all'
Provides-Extra: cli
Requires-Dist: click~=8.1; extra == 'cli'
Provides-Extra: client
Requires-Dist: aenum~=3.1; extra == 'client'
Requires-Dist: aiohttp; extra == 'client'
Requires-Dist: nest-asyncio>=1.5.9,~=1.0; extra == 'client'
Requires-Dist: pillow; extra == 'client'
Requires-Dist: yarl; extra == 'client'
Provides-Extra: default
Requires-Dist: comfy-script[jupyter]; extra == 'default'
Requires-Dist: comfy-script[no-ui]; extra == 'default'
Provides-Extra: jupyter
Requires-Dist: ipywidgets~=8.1; extra == 'jupyter'
Requires-Dist: pillow; extra == 'jupyter'
Requires-Dist: tqdm[notebook]~=4.0; extra == 'jupyter'
Provides-Extra: no-ui
Requires-Dist: comfy-script[client]; extra == 'no-ui'
Requires-Dist: comfy-script[nodes]; extra == 'no-ui'
Requires-Dist: comfy-script[runtime]; extra == 'no-ui'
Requires-Dist: comfy-script[transpile]; extra == 'no-ui'
Provides-Extra: nodes
Requires-Dist: civitai-comfy-nodes; extra == 'nodes'
Requires-Dist: comfyui-ib-customnodes>=0.2.2; extra == 'nodes'
Requires-Dist: comfyui-tooling-nodes; extra == 'nodes'
Provides-Extra: runtime
Requires-Dist: comfy-script[client]; extra == 'runtime'
Requires-Dist: comfy-script[transpile]; extra == 'runtime'
Requires-Dist: pillow; extra == 'runtime'
Requires-Dist: tqdm~=4.0; extra == 'runtime'
Requires-Dist: wrapt~=1.0; extra == 'runtime'
Provides-Extra: solara
Requires-Dist: pillow; extra == 'solara'
Requires-Dist: solara-ui[markdown]~=1.33; extra == 'solara'
Provides-Extra: transpile
Requires-Dist: comfy-script[client]; extra == 'transpile'
Requires-Dist: dynaconf~=3.0; extra == 'transpile'
Requires-Dist: networkx[default]~=3.0; extra == 'transpile'
